django_view_dispatch.py
django_view_dispatch-0.1.dist-info/metadata.json
django_view_dispatch-0.1.dist-info/METADATA
django_view_dispatch-0.1.dist-info/WHEEL
django_view_dispatch-0.1.dist-info/RECORD
django_view_dispatch-0.1.dist-info/top_level.txt
django_view_dispatch-0.1.dist-info/DESCRIPTION.rst
