Metadata-Version: 2.0
Name: django-view-dispatch
Version: 0.1
Summary: Django utility to dispatch views based on request method
Home-page: https://github.com/Psycojoker/django_view_dispatch
Author: Laurent Peuch
Author-email: cortex@worlddomination.be
License: BSD
Keywords: django
Platform: UNKNOWN
Requires-Dist: weirdict
